ProphetLite/__init__.py
ProphetLite/fourier.py
ProphetLite/linear_basis.py
ProphetLite/model.py
ProphetLite/prophetlite.py
ProphetLite-0.0.2.dist-info/LICENSE
ProphetLite-0.0.2.dist-info/METADATA
ProphetLite-0.0.2.dist-info/WHEEL
ProphetLite-0.0.2.dist-info/top_level.txt
ProphetLite-0.0.2.dist-info/RECORD
