Metadata-Version: 2.1
Name: ProphetLite
Version: 0.0.2
Summary: Like Prophet but using Numba and LASSO.
Home-page: https://github.com/tblume1992/ProphetLite
Author: Tyler Blume
Author-email: tblume@mail.USF.edu
Keywords: forecasting,time series,seasonality,trend
Classifier: Programming Language :: Python :: 3
Classifier: License :: OSI Approved :: MIT License
Classifier: Operating System :: OS Independent
License-File: LICENSE
Requires-Dist: numpy
Requires-Dist: matplotlib
Requires-Dist: numba
